{"cameraMode":{"drawMode":0,"name":"Shaded","section":"Shading Mode"},"sceneLighting":true,"audioPlay":false,"sceneViewState":{"m_AlwaysRefresh":false,"showFog":true,"showSkybox":true,"showFlares":true,"showImageEffects":true,"showParticleSystems":true,"showVisualEffectGraphs":true,"m_FxEnabled":true},"in2DMode":false,"pivot":{"x":-14.481156349182129,"y":11.047826766967774,"z":1.2891197204589844},"rotation":{"x":-0.3223112225532532,"y":0.35559260845184328,"z":-0.13214761018753053,"w":-0.86729896068573},"size":11.894824028015137,"orthographic":false}